{
  "1053012308": {
    "code": 10000,
    "msg": "成功",
    "is_logout": 0,
    "data": [
      {
        "sdate": "2022-03-18 18:35:36",
        "edate": null,
        "status": "offline",
        "duration": "3年156天5小时4分",
        "version": "3.2729.1"
      },
      {
        "status": "out",
        "sdate": "2021-08-28 08:44:25",
        "edate": "2021-08-28 10:42:58",
        "duration": "1小时58分",
        "version": "3.6.0"
      },
      {
        "status": "out",
        "sdate": "2021-03-08 08:54:12",
        "edate": "2021-03-08 10:40:21",
        "duration": "1小时46分",
        "version": "3.4.2"
      },
      {
        "status": "out",
        "sdate": "2021-02-03 08:44:42",
        "edate": "2021-02-03 10:40:29",
        "duration": "1小时55分",
        "version": "3.4.2"
      },
      {
        "status": "out",
        "sdate": "2020-05-04 08:37:09",
        "edate": "2020-05-04 10:31:54",
        "duration": "1小时54分",
        "version": "3.2.2"
      },
      {
        "status": "out",
        "sdate": "2020-04-02 08:34:20",
        "edate": "2020-04-02 10:32:52",
        "duration": "1小时58分",
        "version": "3.2.1"
      },
      {
        "status": "out",
        "sdate": "2020-01-28 08:53:12",
        "edate": "2020-01-28 10:52:28",
        "duration": "1小时59分",
        "version": "3.2.1"
      },
      {
        "status": "out",
        "sdate": "2019-11-27 08:53:54",
        "edate": "2019-11-27 11:00:00",
        "duration": "2小时6分",
        "version": "3.2.0"
      },
      {
        "sdate": "2016-01-04 07:41:45",
        "edate": "2022-03-18 18:35:36",
        "status": "online",
        "duration": "6年75天10小时53分",
        "version": "1.0~3.2729.1"
      }
    ],
    "total": 9,
    "pageSize": 20,
    "maxPage": 1,
    "currentPage": 1
  }
}