{
  "1055267582": {
    "code": 10000,
    "msg": "成功",
    "is_logout": 0,
    "data": [
      {
        "sdate": "2020-12-31 04:24:02",
        "edate": null,
        "status": "offline",
        "duration": "4年233天18小时46分",
        "version": "1.1"
      },
      {
        "sdate": "2015-11-12 00:00:00",
        "edate": "2020-12-31 04:24:02",
        "status": "online",
        "duration": "5年51天4小时24分",
        "version": "1.0~1.1"
      }
    ],
    "total": 2,
    "pageSize": 20,
    "maxPage": 1,
    "currentPage": 1
  }
}