{
  "1114692553": {
    "code": 10000,
    "msg": "成功",
    "is_logout": 0,
    "data": [
      {
        "sdate": "2020-11-13 15:52:46",
        "edate": null,
        "status": "offline",
        "duration": "4年281天12小时33分",
        "version": "1.7.3"
      },
      {
        "sdate": "2016-07-12 00:00:00",
        "edate": "2020-11-13 15:52:46",
        "status": "online",
        "duration": "4年125天15小时52分",
        "version": "1.0~1.7.3"
      }
    ],
    "total": 2,
    "pageSize": 20,
    "maxPage": 1,
    "currentPage": 1
  }
}