{
  "1212780112": {
    "code": 10000,
    "msg": "成功",
    "is_logout": 0,
    "data": [
      {
        "sdate": "2023-11-27 11:23:40",
        "edate": null,
        "status": "offline",
        "duration": "1年267天20小时3分",
        "version": "1.0.70"
      },
      {
        "sdate": "2023-02-23 19:55:14",
        "edate": "2023-11-27 11:23:40",
        "status": "online",
        "duration": "276天15小时28分",
        "version": "1.0.70"
      },
      {
        "sdate": "2023-02-22 20:04:08",
        "edate": "2023-02-23 19:55:14",
        "status": "offline",
        "duration": "23小时51分",
        "version": "1.0.70"
      },
      {
        "status": "out",
        "sdate": "2020-04-21 11:34:18",
        "edate": "2020-04-21 13:33:22",
        "duration": "1小时59分",
        "version": "1.0.56"
      },
      {
        "status": "out",
        "sdate": "2020-02-19 03:09:02",
        "edate": "2020-04-18 12:00:00",
        "duration": "59天8小时50分",
        "version": "1.0.55~1.0.56"
      },
      {
        "status": "out",
        "sdate": "2020-01-24 11:40:47",
        "edate": "2020-01-24 13:37:20",
        "duration": "1小时56分",
        "version": "1.0.54"
      },
      {
        "status": "out",
        "sdate": "2019-11-21 10:29:47",
        "edate": "2020-01-22 00:00:00",
        "duration": "61天13小时30分",
        "version": "1.0.52~1.0.54"
      },
      {
        "sdate": "2017-04-06 00:14:28",
        "edate": "2023-02-22 20:04:08",
        "status": "online",
        "duration": "5年323天19小时49分",
        "version": "1.0.16~1.0.70"
      }
    ],
    "total": 8,
    "pageSize": 20,
    "maxPage": 1,
    "currentPage": 1
  }
}