{
  "1235557817": {
    "code": 10000,
    "msg": "成功",
    "is_logout": 0,
    "data": [
      {
        "sdate": "2019-10-29 15:30:38",
        "edate": null,
        "status": "offline",
        "duration": "5年297天16小时8分",
        "version": "3.12.2"
      },
      {
        "status": "out",
        "sdate": "2019-09-29 21:01:25",
        "edate": "2019-09-29 23:00:00",
        "duration": "1小时58分",
        "version": "3.9.6"
      },
      {
        "sdate": "2019-03-27 15:55:58",
        "edate": "2019-10-29 15:30:38",
        "status": "online",
        "duration": "215天23小时34分",
        "version": "2.89.2~3.12.2"
      },
      {
        "sdate": "2018-04-04 17:51:11",
        "edate": "2019-03-27 15:55:58",
        "status": "offline",
        "duration": "356天22小时4分",
        "version": "2.43.1~2.89.2"
      },
      {
        "sdate": "2018-03-15 11:41:34",
        "edate": "2018-04-04 17:51:11",
        "status": "online",
        "duration": "20天6小时9分",
        "version": "2.41.2~2.43.1"
      },
      {
        "sdate": "2018-03-13 04:00:56",
        "edate": "2018-03-15 11:41:34",
        "status": "offline",
        "duration": "2天7小时40分",
        "version": "2.40.6~2.41.2"
      },
      {
        "sdate": "2018-03-12 20:41:34",
        "edate": "2018-03-13 04:00:56",
        "status": "online",
        "duration": "7小时19分",
        "version": "2.40.6"
      },
      {
        "sdate": "2017-11-18 11:13:09",
        "edate": "2018-03-12 20:41:34",
        "status": "offline",
        "duration": "114天9小时28分",
        "version": "2.26.1~2.40.6"
      },
      {
        "sdate": "2017-05-24 03:58:36",
        "edate": "2017-11-18 11:13:09",
        "status": "online",
        "duration": "178天7小时14分",
        "version": "2.1.0~2.26.1"
      }
    ],
    "total": 9,
    "pageSize": 20,
    "maxPage": 1,
    "currentPage": 1
  }
}