{
  "1289254430": {
    "code": 10000,
    "msg": "成功",
    "is_logout": 0,
    "data": [
      {
        "sdate": "2018-04-11 02:50:07",
        "edate": null,
        "status": "offline",
        "duration": "7年134天5小时10分",
        "version": "1.5.3"
      },
      {
        "sdate": "2017-10-12 09:59:42",
        "edate": "2018-04-11 02:50:07",
        "status": "online",
        "duration": "180天16小时50分",
        "version": "1.0~1.5.3"
      }
    ],
    "total": 2,
    "pageSize": 20,
    "maxPage": 1,
    "currentPage": 1
  }
}