{
  "1404804534": {
    "code": 10000,
    "msg": "成功",
    "is_logout": 0,
    "data": [
      {
        "sdate": "2019-01-22 07:32:13",
        "edate": null,
        "status": "offline",
        "duration": "6年213天13小时38分",
        "version": "1.0.0"
      },
      {
        "sdate": "2018-08-01 10:22:56",
        "edate": "2019-01-22 07:32:13",
        "status": "online",
        "duration": "173天21小时9分",
        "version": "1.0.0"
      }
    ],
    "total": 2,
    "pageSize": 20,
    "maxPage": 1,
    "currentPage": 1
  }
}