{
  "1435303295": {
    "code": 10000,
    "msg": "成功",
    "is_logout": 0,
    "data": [
      {
        "sdate": "2024-11-01 15:19:13",
        "edate": "",
        "status": "online",
        "duration": "293天5小时59分",
        "version": "2.0.4"
      },
      {
        "sdate": "2024-10-15 18:50:25",
        "edate": "2024-11-01 15:19:13",
        "status": "offline",
        "duration": "16天20小时28分",
        "version": "2.0.4"
      },
      {
        "status": "out",
        "sdate": "2022-11-30 11:52:05",
        "edate": "2022-11-30 13:59:03",
        "duration": "2小时6分",
        "version": "2.0.1"
      },
      {
        "sdate": "2022-11-29 09:07:01",
        "edate": "2024-10-15 18:50:25",
        "status": "online",
        "duration": "1年321天9小时43分",
        "version": "2.0.1~2.0.4"
      },
      {
        "sdate": "2022-01-26 23:49:05",
        "edate": "2022-11-29 09:07:01",
        "status": "offline",
        "duration": "306天9小时17分",
        "version": "1.9.0~2.0.1"
      },
      {
        "status": "out",
        "sdate": "2019-12-27 02:56:22",
        "edate": "2019-12-27 05:00:00",
        "duration": "2小时3分",
        "version": "1.5.1"
      },
      {
        "status": "out",
        "sdate": "2019-09-21 15:03:22",
        "edate": "2019-09-21 17:00:00",
        "duration": "1小时56分",
        "version": "1.1.0~1.1.1"
      },
      {
        "status": "out",
        "sdate": "2019-08-20 21:27:58",
        "edate": "2019-08-21 00:00:00",
        "duration": "2小时32分",
        "version": "1.1.0"
      },
      {
        "sdate": "2019-04-11 00:00:00",
        "edate": "2022-01-26 23:49:05",
        "status": "online",
        "duration": "2年291天23小时49分",
        "version": "0.9.12~1.9.0"
      },
      {
        "sdate": "2019-01-17 00:00:00",
        "edate": "2019-04-11 00:00:00",
        "status": "preorder",
        "duration": "84天0分",
        "version": "0.9.11~0.9.12"
      }
    ],
    "total": 10,
    "pageSize": 20,
    "maxPage": 1,
    "currentPage": 1
  }
}