{
  "1438702966": {
    "code": 10000,
    "msg": "成功",
    "is_logout": 0,
    "data": [
      {
        "sdate": "2019-03-27 15:23:21",
        "edate": null,
        "status": "offline",
        "duration": "6年149天5小时58分",
        "version": "2.88.1"
      },
      {
        "sdate": "2018-10-29 13:10:52",
        "edate": "2019-03-27 15:23:21",
        "status": "online",
        "duration": "149天2小时12分",
        "version": "2.71.0~2.88.1"
      }
    ],
    "total": 2,
    "pageSize": 20,
    "maxPage": 1,
    "currentPage": 1
  }
}