{
  "1440106401": {
    "code": 10000,
    "msg": "成功",
    "is_logout": 0,
    "data": [
      {
        "sdate": "2020-12-31 03:56:59",
        "edate": null,
        "status": "offline",
        "duration": "4年234天17小时26分",
        "version": "2.3.2"
      },
      {
        "status": "out",
        "sdate": "2019-08-23 21:23:19",
        "edate": "2019-10-23 21:00:00",
        "duration": "60天23小时36分",
        "version": "2.3.2"
      },
      {
        "status": "out",
        "sdate": "2019-08-13 00:04:28",
        "edate": "2019-08-13 02:00:00",
        "duration": "1小时55分",
        "version": "2.3.2"
      },
      {
        "status": "out",
        "sdate": "2019-06-04 23:09:19",
        "edate": "2019-08-04 22:00:00",
        "duration": "60天22小时50分",
        "version": "2.3.1~2.3.2"
      },
      {
        "sdate": "2019-01-18 00:00:00",
        "edate": "2020-12-31 03:56:59",
        "status": "online",
        "duration": "1年348天3小时56分",
        "version": "1.0~2.3.2"
      }
    ],
    "total": 5,
    "pageSize": 20,
    "maxPage": 1,
    "currentPage": 1
  }
}