{
  "1448037588": {
    "code": 10000,
    "msg": "成功",
    "is_logout": 0,
    "data": [
      {
        "sdate": "2020-12-15 18:44:45",
        "edate": null,
        "status": "offline",
        "duration": "4年250天4小时51分",
        "version": "4.1.1"
      },
      {
        "sdate": "2019-01-12 10:18:01",
        "edate": "2020-12-15 18:44:45",
        "status": "online",
        "duration": "1年338天8小时26分",
        "version": "1.0~4.1.1"
      }
    ],
    "total": 2,
    "pageSize": 20,
    "maxPage": 1,
    "currentPage": 1
  }
}