{
  "1450154046": {
    "code": 10000,
    "msg": "成功",
    "is_logout": 0,
    "data": [
      {
        "sdate": "2020-04-22 16:52:49",
        "edate": "",
        "status": "online",
        "duration": "5年122天7小时12分",
        "version": "1.0.7"
      },
      {
        "sdate": "2020-04-21 18:11:24",
        "edate": "2020-04-22 16:52:49",
        "status": "offline",
        "duration": "22小时41分",
        "version": "1.0.7"
      },
      {
        "sdate": "2019-09-13 20:37:05",
        "edate": "2020-04-21 18:11:24",
        "status": "online",
        "duration": "220天21小时34分",
        "version": "1.0.5~1.0.7"
      },
      {
        "sdate": "2019-09-13 18:46:44",
        "edate": "2019-09-13 20:37:05",
        "status": "offline",
        "duration": "1小时50分",
        "version": "1.0.5"
      },
      {
        "sdate": "2019-04-10 00:00:00",
        "edate": "2019-09-13 18:46:44",
        "status": "online",
        "duration": "156天18小时46分",
        "version": "1.0.1~1.0.5"
      },
      {
        "sdate": "2019-01-26 19:32:17",
        "edate": "2019-04-10 00:00:00",
        "status": "preorder",
        "duration": "73天4小时27分",
        "version": "1.0.0~1.0.1"
      }
    ],
    "total": 6,
    "pageSize": 20,
    "maxPage": 1,
    "currentPage": 1
  }
}