{
  "1473788306": {
    "code": 10000,
    "msg": "成功",
    "is_logout": 0,
    "data": [
      {
        "sdate": "2020-02-26 14:38:52",
        "edate": null,
        "status": "offline",
        "duration": "5年178天9小时58分",
        "version": "1.4.1"
      },
      {
        "sdate": "2019-10-30 00:50:32",
        "edate": "2020-02-26 14:38:52",
        "status": "online",
        "duration": "119天13小时48分",
        "version": "1.0.0~1.4.1"
      }
    ],
    "total": 2,
    "pageSize": 20,
    "maxPage": 1,
    "currentPage": 1
  }
}