{
  "1476786764": {
    "code": 10000,
    "msg": "成功",
    "is_logout": 0,
    "data": [
      {
        "sdate": "2023-09-20 15:04:15",
        "edate": null,
        "status": "offline",
        "duration": "1年336天9小时37分",
        "version": "1.0.22"
      },
      {
        "sdate": "2022-01-01 20:50:04",
        "edate": "2023-09-20 15:04:15",
        "status": "online",
        "duration": "1年261天18小时14分",
        "version": "1.0.21~1.0.22"
      },
      {
        "sdate": "2021-12-24 01:22:54",
        "edate": "2022-01-01 20:50:04",
        "status": "offline",
        "duration": "8天19小时27分",
        "version": "1.0.20~1.0.21"
      },
      {
        "sdate": "2021-12-23 12:49:16",
        "edate": "2021-12-24 01:22:54",
        "status": "online",
        "duration": "12小时33分",
        "version": "1.0.20"
      },
      {
        "sdate": "2021-12-06 15:56:53",
        "edate": "2021-12-23 12:49:16",
        "status": "offline",
        "duration": "16天20小时52分",
        "version": "1.0.20"
      },
      {
        "sdate": "2021-01-08 06:44:01",
        "edate": "2021-12-06 15:56:53",
        "status": "online",
        "duration": "332天9小时12分",
        "version": "1.0.18~1.0.20"
      },
      {
        "sdate": "2020-12-31 05:33:26",
        "edate": "2021-01-08 06:44:01",
        "status": "offline",
        "duration": "8天1小时10分",
        "version": "1.0.17~1.0.18"
      },
      {
        "status": "out",
        "sdate": "2020-05-10 05:28:49",
        "edate": "2020-05-10 07:28:38",
        "duration": "1小时59分",
        "version": "1.0.15"
      },
      {
        "status": "out",
        "sdate": "2019-10-18 14:39:28",
        "edate": "2019-10-18 17:00:00",
        "duration": "2小时20分",
        "version": "1.0.5"
      },
      {
        "sdate": "2019-10-17 00:00:00",
        "edate": "2020-12-31 05:33:26",
        "status": "online",
        "duration": "1年76天5小时33分",
        "version": "1.0.3~1.0.17"
      },
      {
        "sdate": "2019-09-28 00:18:04",
        "edate": "2019-10-17 00:00:00",
        "status": "preorder",
        "duration": "18天23小时41分",
        "version": "1.0.0~1.0.3"
      }
    ],
    "total": 11,
    "pageSize": 20,
    "maxPage": 1,
    "currentPage": 1
  }
}