{
  "1478916024": {
    "code": 10000,
    "msg": "成功",
    "is_logout": 0,
    "data": [
      {
        "sdate": "2020-12-31 03:59:28",
        "edate": null,
        "status": "offline",
        "duration": "4年234天20小时46分",
        "version": "1.0.47"
      },
      {
        "sdate": "2020-01-29 00:00:00",
        "edate": "2020-12-31 03:59:28",
        "status": "online",
        "duration": "337天3小时59分",
        "version": "1.0~1.0.47"
      }
    ],
    "total": 2,
    "pageSize": 20,
    "maxPage": 1,
    "currentPage": 1
  }
}