{
  "1535751765": {
    "code": 10000,
    "msg": "成功",
    "is_logout": 0,
    "data": [
      {
        "sdate": "2022-03-04 20:21:40",
        "edate": null,
        "status": "offline",
        "duration": "3年171天9小时46分",
        "version": "1.7.1"
      },
      {
        "sdate": "2020-10-15 00:00:00",
        "edate": "2022-03-04 20:21:40",
        "status": "online",
        "duration": "1年140天20小时21分",
        "version": "1.0.0~1.7.1"
      }
    ],
    "total": 2,
    "pageSize": 20,
    "maxPage": 1,
    "currentPage": 1
  }
}