{
  "1539650884": {
    "code": 10000,
    "msg": "成功",
    "is_logout": 0,
    "data": [
      {
        "sdate": "2021-08-12 21:50:16",
        "edate": null,
        "status": "offline",
        "duration": "4年10天8小时21分",
        "version": "2.5.3"
      },
      {
        "status": "out",
        "sdate": "2020-11-29 15:22:33",
        "edate": "2020-11-29 16:48:31",
        "duration": "1小时25分",
        "version": "2.5.1"
      },
      {
        "sdate": "2020-11-12 00:00:00",
        "edate": "2021-08-12 21:50:16",
        "status": "online",
        "duration": "273天21小时50分",
        "version": "2.5~2.5.3"
      }
    ],
    "total": 3,
    "pageSize": 20,
    "maxPage": 1,
    "currentPage": 1
  }
}