{
  "1581598210": {
    "code": 10000,
    "msg": "成功",
    "is_logout": 0,
    "data": [
      {
        "sdate": "2024-10-21 16:21:14",
        "edate": "",
        "status": "online",
        "duration": "304天23小时32分",
        "version": "2.0.14"
      },
      {
        "sdate": "2023-02-20 20:09:42",
        "edate": "2024-10-21 16:21:14",
        "status": "offline",
        "duration": "1年243天20小时11分",
        "version": "2.0.14"
      },
      {
        "sdate": "2022-03-02 02:06:30",
        "edate": "2023-02-20 20:09:42",
        "status": "online",
        "duration": "355天18小时3分",
        "version": "1.0.23~2.0.14"
      },
      {
        "sdate": "2022-01-06 00:36:43",
        "edate": "2022-03-02 02:06:30",
        "status": "offline",
        "duration": "55天1小时29分",
        "version": "1.0.23"
      },
      {
        "status": "out",
        "sdate": "2021-11-19 18:08:17",
        "edate": "2021-11-19 19:56:03",
        "duration": "1小时47分",
        "version": "1.0.21"
      },
      {
        "status": "out",
        "sdate": "2021-10-14 18:14:02",
        "edate": "2021-10-14 20:06:08",
        "duration": "1小时52分",
        "version": "1.0.12"
      },
      {
        "status": "out",
        "sdate": "2021-09-09 11:57:04",
        "edate": "2021-09-09 14:03:03",
        "duration": "2小时5分",
        "version": "1.0.5"
      },
      {
        "sdate": "2021-08-17 00:00:00",
        "edate": "2022-01-06 00:36:43",
        "status": "online",
        "duration": "142天36分",
        "version": "1.0~1.0.23"
      }
    ],
    "total": 8,
    "pageSize": 20,
    "maxPage": 1,
    "currentPage": 1
  }
}