{
  "1592580546": {
    "code": 10000,
    "msg": "成功",
    "is_logout": 0,
    "data": [
      {
        "sdate": "2024-12-21 05:15:19",
        "edate": null,
        "status": "offline",
        "duration": "244天10小时42分",
        "version": "1.3"
      },
      {
        "sdate": "2021-10-29 00:00:00",
        "edate": "2024-12-21 05:15:19",
        "status": "online",
        "duration": "3年54天5小时15分",
        "version": "1.0~1.3"
      }
    ],
    "total": 2,
    "pageSize": 20,
    "maxPage": 1,
    "currentPage": 1
  }
}