{
  "971233157": {
    "code": 10000,
    "msg": "成功",
    "is_logout": 0,
    "data": [
      {
        "sdate": "2020-01-07 19:36:49",
        "edate": null,
        "status": "offline",
        "duration": "5年227天2小时36分",
        "version": "1.9.0"
      },
      {
        "sdate": "2016-10-26 09:02:59",
        "edate": "2020-01-07 19:36:49",
        "status": "online",
        "duration": "3年73天10小时33分",
        "version": "1.0.3~1.9.0"
      }
    ],
    "total": 2,
    "pageSize": 20,
    "maxPage": 1,
    "currentPage": 1
  }
}